django_property_filter/__init__.py
django_property_filter/constants.py
django_property_filter/filters.py
django_property_filter/filtersets.py
django_property_filter/utils.py
tests/tests/__init__.py
tests/tests/test_common.py
tests/tests/test_django_filter_app.py
django_property_filter-1.2.0.dist-info/LICENSE
django_property_filter-1.2.0.dist-info/METADATA
django_property_filter-1.2.0.dist-info/WHEEL
django_property_filter-1.2.0.dist-info/top_level.txt
django_property_filter-1.2.0.dist-info/RECORD
