Metadata-Version: 2.1
Name: django-property-filter
Version: 1.2.0
Summary: Django Filter extension to support filtering by Properties
Author: Eric Ziethen
Author-email: ericziethen@gmail.com
License: MIT
Project-URL: Documentation, https://django-property-filter.readthedocs.io/en/stable/
Project-URL: Changelog, https://github.com/ericziethen/django-property-filter/blob/master/CHANGELOG.md
Project-URL: Public Issue Reporting, https://github.com/ericziethen/django-property-filter-issue-reporting
Project-URL: Source Code, https://github.com/ericziethen/django-property-filter
Platform: any
Classifier: Development Status :: 5 - Production/Stable
Classifier: Intended Audience :: Developers
Classifier: License :: OSI Approved :: MIT License
Classifier: Operating System :: OS Independent
Classifier: Framework :: Django
Classifier: Framework :: Django :: 3.2
Classifier: Framework :: Django :: 4.0
Classifier: Framework :: Django :: 4.1
Classifier: Framework :: Django :: 5.0
Classifier: Programming Language :: Python
Classifier: Programming Language :: Python :: 3
Classifier: Programming Language :: Python :: 3.7
Classifier: Programming Language :: Python :: 3.8
Classifier: Programming Language :: Python :: 3.9
Classifier: Programming Language :: Python :: 3.10
Classifier: Programming Language :: Python :: 3.11
Classifier: Programming Language :: Python :: 3.12
Classifier: Topic :: Software Development :: Libraries :: Python Modules
Requires-Python: >=3.7
License-File: LICENSE
Requires-Dist: Django >=3.2
Requires-Dist: django-filter >=2.3.0
